{"TD": [460.24, 2185, 2007.4, 2343.98], "TSR": [{"bbox": [492, 2189, 650, 2254], "column_nums": [0], "row_nums": [0], "column_header": true, "subcell": false, "projected_row_header": false, "cell_text": "Turkey", "normalized_cell_text": "Turkey"}, {"bbox": [934, 2199, 1044, 2241], "column_nums": [1], "row_nums": [0], "column_header": true, "subcell": false, "projected_row_header": false, "cell_text": "4.464", "normalized_cell_text": "4.464"}, {"bbox": [1226, 2193, 1342, 2244], "column_nums": [2], "row_nums": [0], "column_header": true, "subcell": false, "projected_row_header": false, "cell_text": "2.545", "normalized_cell_text": "2.545"}, {"bbox": [1514, 2193, 1630, 2244], "column_nums": [3], "row_nums": [0], "column_header": true, "subcell": false, "projected_row_header": false, "cell_text": "1.802", "normalized_cell_text": "1.802"}, {"bbox": [1788, 2193, 1904, 2244], "column_nums": [4], "row_nums": [0], "column_header": true, "subcell": false, "projected_row_header": false, "cell_text": "3.586", "normalized_cell_text": "3.586"}, {"bbox": [496, 2244, 835, 2309], "column_nums": [0], "row_nums": [1], "column_header": false, "subcell": false, "projected_row_header": false, "cell_text": "United Kingdom", "normalized_cell_text": "United Kingdom"}, {"bbox": [931, 2244, 1051, 2295], "column_nums": [1], "row_nums": [1], "column_header": false, "subcell": false, "projected_row_header": false, "cell_text": "9.832", "normalized_cell_text": "9.832"}, {"bbox": [1216, 2247, 1356, 2299], "column_nums": [2], "row_nums": [1], "column_header": false, "subcell": false, "projected_row_header": false, "cell_text": "10.087", "normalized_cell_text": "10.087"}, {"bbox": [1510, 2247, 1630, 2299], "column_nums": [3], "row_nums": [1], "column_header": false, "subcell": false, "projected_row_header": false, "cell_text": "6.067", "normalized_cell_text": "6.067"}, {"bbox": [1778, 2247, 1911, 2299], "column_nums": [4], "row_nums": [1], "column_header": false, "subcell": false, "projected_row_header": false, "cell_text": "18.611", "normalized_cell_text": "18.611"}]}